RabbitMqHttp.py
robotframework_http_rabbitmq-1.0.3.dist-info/LICENSE
robotframework_http_rabbitmq-1.0.3.dist-info/METADATA
robotframework_http_rabbitmq-1.0.3.dist-info/WHEEL
robotframework_http_rabbitmq-1.0.3.dist-info/top_level.txt
robotframework_http_rabbitmq-1.0.3.dist-info/RECORD
