Metadata-Version: 2.1
Name: robotframework-http-rabbitmq
Version: 1.0.3
Summary: A Robot Framework RabbitMq Library
Home-page: https://github.com/adsith-pv/robotframework-http-rabbitmq
Author: Carlos Alvarez
Author-email: c.alvarez@payvision.com
License: Apache License 2.0
Keywords: testing testautomation robotframework rabbitmq http
Platform: UNKNOWN
Classifier: Development Status :: 5 - Production/Stable
Classifier: Intended Audience :: Developers
Classifier: Topic :: Software Development :: Testing
Classifier: License :: OSI Approved :: Apache Software License
Classifier: Programming Language :: Python :: 3.5
Classifier: Programming Language :: Python :: 3.6
Classifier: Framework :: Robot Framework :: Library
Requires-Dist: requests (>=2.20.0)
Requires-Dist: robotframework (>=3.0.4)
